indor/__init__.py
indor/__main__.py
indor/assert_.py
indor/assign.py
indor/command.py
indor/command_factory.py
indor/command_path.py
indor/command_register.py
indor/command_response.py
indor/commands.py
indor/connect.py
indor/general_error.py
indor/indor_exceptions.py
indor/input_parser.py
indor/logo.txt
indor/main.py
indor/parsed_value.py
indor/parsers_to_xml_tree.py
indor/parsing_exception.py
indor/printer.py
indor/reading.py
indor/relational_operators.py
indor/result.py
indor/result_collector.py
indor/scenario.py
indor/scenario_data.py
indor/scenario_results.py
indor/select_parser.py
indor/singleton.py
indor/statistics.py
indor/test.py
indor/test_results.py
indor/test_runner.py
indor/transform_nested_array.py
indor/xml_tree.py
indor/xml_tree_factory.py
indor/xml_tree_register.py
indor-0.3.dist-info/DESCRIPTION.rst
indor-0.3.dist-info/METADATA
indor-0.3.dist-info/RECORD
indor-0.3.dist-info/WHEEL
indor-0.3.dist-info/entry_points.txt
indor-0.3.dist-info/metadata.json
indor-0.3.dist-info/top_level.txt
