Metadata-Version: 2.0
Name: indor
Version: 0.3
Summary: Tool for running rest-api tests written in plain language.
Home-page: https://github.com/nokia-wroclaw/innovativeproject-resttest
Author: Sławomir Domagała, Damian Mirecki, Tomasz Wlisłocki, Bartosz Zięba
Author-email: UNKNOWN
License: UNKNOWN
Platform: UNKNOWN
Requires-Dist: junit-xml
Requires-Dist: pyparsing
Requires-Dist: requests
Requires-Dist: termcolor
